{
  "file_path": "/home/kathirks_gc/v8_go/codebase/src/base/numbers/diy-fp.cc",
  "imports": [
    "src/base/numbers/diy-fp.h",
    "stdint.h"
  ],
  "classes": [
    {
      "name": "DiyFp",
      "properties": [
        "f_",
        "e_"
      ],
      "methods": [
        {
          "name": "Multiply",
          "parameters": [
            "const DiyFp& other"
          ],
          "return_type": "void",
          "logic": "Multiplies this DiyFp number with another DiyFp number. It emulates a 128-bit multiplication using 64-bit integers and stores the result in the current DiyFp object. It also updates the exponent 'e_' accordingly and performs rounding."
        }
      ]
    }
  ],
  "functions": []
}