{
  "file_path": "/home/kathirks_gc/v8_go/codebase/src/compiler/wasm-inlining-into-js.h",
  "imports": [
    "src/base/vector.h",
    "src/common/globals.h"
  ],
  "classes": [
    {
      "name": "WasmIntoJSInliner",
      "properties": [],
      "methods": [
        {
          "name": "TryInlining",
          "parameters": [
            "Zone* zone",
            "const wasm::WasmModule* module",
            "MachineGraph* mcgraph",
            "const wasm::FunctionBody& body",
            "base::Vector<const uint8_t> bytes",
            "SourcePositionTable* source_position_table",
            "int inlining_id"
          ],
          "return_type": "bool",
          "logic": "Attempts to inline a small WebAssembly function into JavaScript.  It checks if the function only contains specific, supported instructions.  It returns true if inlining was successful, false otherwise."
        }
      ]
    }
  ],
  "functions": []
}